{"url": "https://article.wn.com/view/2017/08/27/Pregnant_Jenny_Mollen_Shows_Dramatic_BeforeandAfter_Baby_Bum/", "text": "Lookin' good, mama! New York Times best-selling writer and actress Jenny Mollen, who is married to actor Jason Biggs, showed the difference 33 weeks (and a bun in the over) can... ...... read full story", "images": ["https://ecdn4.wn.com/or/assets/assets/wn/img/logo.png", "https://ecdn0.wn.com/st/favicon-20131209.ico"], "top_img": "https://ecdn0.wn.com/st/favicon-20131209.ico", "keywords": [], "authors": [], "canonical_link": "https://article.wn.com/view/2017/08/27/Pregnant_Jenny_Mollen_Shows_Dramatic_BeforeandAfter_Baby_Bum/", "title": "Pregnant Jenny Mollen Shows Dramatic Before-and-After Baby Bump Photo", "meta_data": {"referrer": "no-referrer-when-downgrade", "viewport": "width=device-width, initial-scale=1, maximum-scale=1, minimum-scale=1, user-scalable=no", "keywords": "showbiz", "description": "Lookin' good, mama! New York Times best-selling writer and actress Jenny Mollen, who is married to actor Jason Biggs, showed the difference 33 weeks (and a bun in the over) can... ...", "twitter": {"card": "summary_large_image", "site": "@worldnewsdotcom", "title": "Pregnant Jenny Mollen Shows Dramatic Before-and-After Baby Bump Photo"}}, "movies": [], "publish_date": 1503806400.0, "source": "https://article.wn.com", "summary": ""}