{"url": "mashable.com/2018/03/28/dawsons-creek-reunion-katie-holmes-joshua-jackson-love/", "text": "Joey Potter and Pacey Witter still look crazy in love, and Dawson's Creek fans are overjoyed to the point of tears.\n\nThe cast of the teen drama recently reunited to celebrate the show's 20th anniversary for a special edition of Entertainment Weekly. After reviewing the flawless photoshoot one thing stood out: Katie Holmes and Joshua Jackson looking truly, madly, and deeply in love.\n\nHolmes and Jackson played Joey and Pacey, respectively, one of the show's greatest ships, so to see them lovingly touching each other like time had damn near frozen in 2003 was A LOT to handle.\n\nPerceptive fans immediately picked up on the chemistry between the two actors and it was as if the rest of the cast wasn't even there.\n\nMashable Top Stories Stay connected with the hottest stories of the day and the latest entertainment news. Sign up for Mashable's Top Stories newsletter Loading... Sign Me Up Use this instead By clicking Sign Me Up, you confirm you are 16+ and agree to our Terms of Use and Privacy Policy Thanks for signing up!\n\nI mean, look at Holmes resting her hands on Jackson's shoulders.\n\nAnd then Jackson RESTED HIS HEAD on Holmes' shoulder and put his hand on her back. Are you kidding me?\n\nThey even wore the same hat and it was all just very overwhelming, okay?!!\n\nWe. Remember. Everything.\n\n[h/t:BuzzFeed]\n\nFeatured Video For You Here's why 'Missed Connections' is no longer featured on Craigslist", "images": ["https://helios-i.mashable.com/imagery/articles/007aprr18SK6DiSx308LfOO/hero-image.fill.size_220x133.v1763392633.jpg", "https://helios-i.mashable.com/imagery/articles/07wVV9SG2isrcbclPm0H1cc/hero-image.fill.size_220x220.v1763394060.jpg", "https://helios-i.mashable.com/imagery/articles/05tcqfUm6RJocaIyNwNUFA3/hero-image.fill.size_220x133.v1758122666.png", "https://helios-i.mashable.com/imagery/videos/07xblCEbCHSAze1IGtF5ZLP/hero-image.fill.size_220x220.v1762454682.jpg", "https://helios-i.mashable.com/imagery/articles/03vkYI5W2WeG7n7smqWnUf5/hero-image.fill.size_220x133.v1761130467.jpg", "https://helios-i.mashable.com/imagery/videos/025F4UKcTZmgwBv2VDceU47/hero-image.fill.size_220x133.v1760476930.jpg", "https://helios-i.mashable.com/imagery/articles/007aprr18SK6DiSx308LfOO/hero-image.fill.size_220x220.v1763392633.jpg", "https://helios-i.mashable.com/imagery/authors/068SXUC8MJuzQVkfRzyqp17/image.fill.size_100x100.v1624381066.jpg", "https://helios-i.mashable.com/imagery/videos/025F4UKcTZmgwBv2VDceU47/hero-image.fill.size_220x220.v1760476930.jpg", "https://helios-i.mashable.com/imagery/articles/028TjWWY1KwjqZZ1eqqH9Hh/hero-image.fill.size_220x220.v1756140131.jpg", "https://c.evidon.com/pub/icong1.png", "https://helios-i.mashable.com/imagery/videos/07xblCEbCHSAze1IGtF5ZLP/hero-image.fill.size_220x133.v1762454682.jpg", "https://helios-i.mashable.com/imagery/articles/076VV8mAxGBVqqpx9AseY7d/hero-image.fill.size_220x133.v1763394888.jpg", "https://helios-i.mashable.com/imagery/articles/05Cc9r1sCIzFBKPx2ATtc3G/hero-image.fill.size_220x220.v1763392483.jpg", "https://helios-i.mashable.com/imagery/articles/04VCPAk1eJ8kHMuseFAojiF/hero-image.fill.size_1200x675.1.jpg", "https://helios-i.mashable.com/imagery/articles/05Cc9r1sCIzFBKPx2ATtc3G/hero-image.fill.size_220x133.v1763392483.jpg", "https://helios-i.mashable.com/imagery/articles/001rZ0nZbCDH7L015QnLl0n/hero-image.fill.size_220x220.v1763394491.jpg", "https://helios-i.mashable.com/imagery/articles/07wVV9SG2isrcbclPm0H1cc/hero-image.fill.size_220x133.v1763394060.jpg", "https://helios-i.mashable.com/imagery/articles/05tcqfUm6RJocaIyNwNUFA3/hero-image.fill.size_220x220.v1758122666.png", "http://mashable.com/images/seamless-keep-scrolling.png", "https://helios-i.mashable.com/imagery/articles/028TjWWY1KwjqZZ1eqqH9Hh/hero-image.fill.size_220x133.v1756140131.jpg", "https://helios-i.mashable.com/imagery/articles/03vkYI5W2WeG7n7smqWnUf5/hero-image.fill.size_220x220.v1761130467.jpg", "https://helios-i.mashable.com/imagery/authors/068SXUC8MJuzQVkfRzyqp17/image.fill.size_200x200.v1624381066.jpg", "https://helios-i.mashable.com/imagery/articles/076VV8mAxGBVqqpx9AseY7d/hero-image.fill.size_220x220.v1763394888.jpg", "https://helios-i.mashable.com/imagery/articles/001rZ0nZbCDH7L015QnLl0n/hero-image.fill.size_220x133.v1763394491.jpg"], "top_img": "https://helios-i.mashable.com/imagery/articles/04VCPAk1eJ8kHMuseFAojiF/hero-image.fill.size_1200x675.1.jpg", "keywords": [], "authors": [], "canonical_link": "https://mashable.com/article/dawsons-creek-reunion-katie-holmes-joshua-jackson-love", "title": "Katie Holmes and Joshua Jackson looked VERY lovey-dovey at that 'Dawson's Creek' reunion", "meta_data": {"viewport": "width=device-width, initial-scale=1", "theme-color": "#00aeef", "application-name": "Mashable.com", "description": "Katie Holmes and Joshua Jackson look extremely precious in the 'Dawson's Creek' revival photos.", "fb": {"app_id": 122071082108, "pages": 18807449704}, "og": {"site_name": "Mashable", "title": "Katie Holmes and Joshua Jackson looked VERY lovey-dovey at that 'Dawson's Creek' reunion", "url": "https://mashable.com/article/dawsons-creek-reunion-katie-holmes-joshua-jackson-love", "description": "\ud83d\udc40 Don't cry, Dawson. \ud83d\udc40", "image": {"identifier": "https://helios-i.mashable.com/imagery/articles/04VCPAk1eJ8kHMuseFAojiF/hero-image.fill.size_1200x675.1.jpg", "secure_url": "https://helios-i.mashable.com/imagery/articles/04VCPAk1eJ8kHMuseFAojiF/hero-image.fill.size_1200x675.1.jpg", "height": 675, "width": 1200}, "type": "article", "article": {"tag": "Celebrities"}}, "article": {"author": "Nicole Gallucci", "published_time": "2018-03-28T21:29:31+00:00", "section": "Entertainment"}, "twitter": {"site": "@mashable", "card": "summary_large_image", "creator": "@mashable", "title": "Katie Holmes and Joshua Jackson looked VERY lovey-dovey at that 'Dawson's Creek' reunion", "description": "\ud83d\udc40 Don't cry, Dawson. \ud83d\udc40", "image": "https://helios-i.mashable.com/imagery/articles/04VCPAk1eJ8kHMuseFAojiF/hero-image.fill.size_1200x675.1.jpg"}, "robots": "max-image-preview:large"}, "movies": [], "publish_date": 1522209600.0, "source": "http://mashable.com", "summary": ""}