{"url": "https://mashable.com/2017/11/03/millie-bobby-brown-kardashians-on-twitter/", "text": "They're all each other's biggest fans.\n\nThey're all each other's biggest fans. Credit: MediaPunch/REX/Shutterstock/S Meddle/ITV/REX/Shutterstock/mashable composite\n\nWhat is this, a crossover episode?\n\nOn Tuesday night Millie Bobby Brown (a.k.a. Eleven from Stranger Things) went on The Tonight Show with Jimmy Fallon and revealed that she loves Keeping Up with the Kardashians.\n\nIt was only a matter of time before the Kardashian clan saw this.\n\nMashable Top Stories Stay connected with the hottest stories of the day and the latest entertainment news. Sign up for Mashable's Top Stories newsletter Loading... Sign Me Up Use this instead By clicking Sign Me Up, you confirm you are 16+ and agree to our Terms of Use and Privacy Policy Thanks for signing up!\n\nMillie was happy to see the Kardashians' responses.\n\nThe rest of Twitter was delighted to see such an exchange of admiration.\n\nIt's nice to see people supporting each other on Twitter, rather than tearing each other apart. Keep the love going ladies!\n\nFeatured Video For You This MIT professor with a reality show is the Kardashian of physics", "images": ["https://mashable.com/images/seamless-keep-scrolling.png", "https://helios-i.mashable.com/imagery/videos/05RVnAVG0FP5gKWLeDH8Yle/hero-image.fill.size_220x133.v1760975360.jpg", "https://helios-i.mashable.com/imagery/videos/02N2U4yvoJZY66s679mCapT/hero-image.fill.size_220x220.v1762468074.jpg", "https://helios-i.mashable.com/imagery/articles/07wVV9SG2isrcbclPm0H1cc/hero-image.fill.size_220x220.v1763394060.jpg", "https://helios-i.mashable.com/imagery/videos/05RVnAVG0FP5gKWLeDH8Yle/hero-image.fill.size_220x220.v1760975360.jpg", "https://helios-i.mashable.com/imagery/articles/05Wbr4YYgFjflibVC0EUvYd/hero-image.fill.size_220x220.v1763530604.png", "https://helios-i.mashable.com/imagery/videos/01Ffder9nq5hOFXNSzlR6ej/hero-image.fill.size_220x220.v1755798247.jpg", "https://c.evidon.com/pub/icong1.png", "https://helios-i.mashable.com/imagery/articles/06P5SP90pWUVTYtFoYHHzAD/hero-image.fill.size_1248x702.v1623366997.jpg", "https://helios-i.mashable.com/imagery/videos/047G6etG14qo4NOzIpvJF7N/hero-image.fill.size_220x220.v1761162820.jpg", "https://helios-i.mashable.com/imagery/articles/076VV8mAxGBVqqpx9AseY7d/hero-image.fill.size_220x133.v1763394888.jpg", "https://helios-i.mashable.com/imagery/videos/02N2U4yvoJZY66s679mCapT/hero-image.fill.size_220x133.v1762468074.jpg", "https://helios-i.mashable.com/imagery/videos/01Ffder9nq5hOFXNSzlR6ej/hero-image.fill.size_220x133.v1755798247.jpg", "https://helios-i.mashable.com/imagery/articles/04HyercZsbeCC1yac4jUTN2/hero-image.fill.size_220x220.v1762984243.png", "https://helios-i.mashable.com/imagery/videos/047G6etG14qo4NOzIpvJF7N/hero-image.fill.size_220x133.v1761162820.jpg", "https://helios-i.mashable.com/imagery/articles/05QrTBLI5pXdN8guS10tMcI/hero-image.fill.size_220x220.v1763394683.jpg", "https://helios-i.mashable.com/imagery/articles/001rZ0nZbCDH7L015QnLl0n/hero-image.fill.size_220x220.v1763394491.jpg", "https://helios-i.mashable.com/imagery/articles/06P5SP90pWUVTYtFoYHHzAD/hero-image.fill.size_1200x675.v1623366997.jpg", "https://helios-i.mashable.com/imagery/articles/05QrTBLI5pXdN8guS10tMcI/hero-image.fill.size_220x133.v1763394683.jpg", "https://helios-i.mashable.com/imagery/articles/05Wbr4YYgFjflibVC0EUvYd/hero-image.fill.size_220x133.v1763530604.png", "https://helios-i.mashable.com/imagery/articles/07wVV9SG2isrcbclPm0H1cc/hero-image.fill.size_220x133.v1763394060.jpg", "https://helios-i.mashable.com/imagery/articles/04HyercZsbeCC1yac4jUTN2/hero-image.fill.size_220x133.v1762984243.png", "https://helios-i.mashable.com/imagery/articles/076VV8mAxGBVqqpx9AseY7d/hero-image.fill.size_220x220.v1763394888.jpg", "https://helios-i.mashable.com/imagery/articles/001rZ0nZbCDH7L015QnLl0n/hero-image.fill.size_220x133.v1763394491.jpg"], "top_img": "https://helios-i.mashable.com/imagery/articles/06P5SP90pWUVTYtFoYHHzAD/hero-image.fill.size_1200x675.v1623366997.jpg", "keywords": [], "authors": [], "canonical_link": "https://mashable.com/article/millie-bobby-brown-kardashians-on-twitter", "title": "Millie Bobby Brown and the Kardashians are each others' biggest fans", "meta_data": {"viewport": "width=device-width, initial-scale=1", "theme-color": "#00aeef", "application-name": "Mashable.com", "description": "Following Millie Bobby Brown's appearance on 'The Tonight Show' the Kardashians reached out on Twitter to show their appreciation for her work.", "fb": {"app_id": 122071082108, "pages": 18807449704}, "og": {"site_name": "Mashable", "title": "Millie Bobby Brown and the Kardashians are each others' biggest fans", "url": "https://mashable.com/article/millie-bobby-brown-kardashians-on-twitter", "description": "Worlds collide!", "image": {"identifier": "https://helios-i.mashable.com/imagery/articles/06P5SP90pWUVTYtFoYHHzAD/hero-image.fill.size_1200x675.v1623366997.jpg", "secure_url": "https://helios-i.mashable.com/imagery/articles/06P5SP90pWUVTYtFoYHHzAD/hero-image.fill.size_1200x675.v1623366997.jpg", "height": 675, "width": 1200}, "type": "article", "article": {"tag": "Celebrities"}}, "article": {"author": "Isobel Hamilton", "published_time": "2017-11-03T11:14:16+00:00", "section": "Entertainment"}, "twitter": {"site": "@mashable", "card": "summary_large_image", "creator": "@mashable", "title": "Millie Bobby Brown and the Kardashians are each others' biggest fans", "description": "Worlds collide!", "image": "https://helios-i.mashable.com/imagery/articles/06P5SP90pWUVTYtFoYHHzAD/hero-image.fill.size_1200x675.v1623366997.jpg"}, "robots": "max-image-preview:large"}, "movies": [], "publish_date": 1509681600.0, "source": "https://mashable.com", "summary": ""}